setup.py
Flask_OAuth2_Login.egg-info/PKG-INFO
Flask_OAuth2_Login.egg-info/SOURCES.txt
Flask_OAuth2_Login.egg-info/dependency_links.txt
Flask_OAuth2_Login.egg-info/requires.txt
Flask_OAuth2_Login.egg-info/top_level.txt
flask_oauth2_login/__init__.py
flask_oauth2_login/base.py
flask_oauth2_login/coursera.py
flask_oauth2_login/google.py
flask_oauth2_login/linkedin.py